localhost_on_colab/__init__.py
localhost_on_colab/core.py
localhost_on_colab-0.0.0.dist-info/METADATA
localhost_on_colab-0.0.0.dist-info/WHEEL
localhost_on_colab-0.0.0.dist-info/top_level.txt
localhost_on_colab-0.0.0.dist-info/RECORD
