Metadata-Version: 2.1
Name: localhost-on-colab
Version: 0.0.0
Summary: Helps you run localhost stuff on colab
Home-page: https://github.com/Mayukhdeb/localhost-on-colab
Author: Mayukh Deb
Author-email: mayukhmainak2000@gmail.com
License: UNKNOWN
Platform: UNKNOWN
Classifier: Natural Language :: English
Classifier: Topic :: Software Development :: Libraries :: Python Modules
Requires-Python: >=3.6
Requires-Dist: pyngrok (>=5.0.5)
Requires-Dist: PyYAML (>=5.4.1)
